jmstate/__init__.py
jmstate/py.typed
jmstate/functions/__init__.py
jmstate/functions/_base_hazards.py
jmstate/functions/_individual_effects.py
jmstate/functions/_regression_and_link.py
jmstate/jobs/__init__.py
jmstate/jobs/_computation.py
jmstate/jobs/_fitting.py
jmstate/jobs/_logging.py
jmstate/jobs/_prediction.py
jmstate/jobs/_projection.py
jmstate/jobs/_stopping.py
jmstate/model/__init__.py
jmstate/model/_base.py
jmstate/model/_cache.py
jmstate/model/_hazard.py
jmstate/model/_longitudinal.py
jmstate/model/_prior.py
jmstate/model/_sampler.py
jmstate/typedefs/__init__.py
jmstate/typedefs/_data.py
jmstate/typedefs/_defaults.py
jmstate/typedefs/_defs.py
jmstate/typedefs/_params.py
jmstate/typedefs/_validators.py
jmstate/utils/__init__.py
jmstate/utils/_checks.py
jmstate/utils/_dtype.py
jmstate/utils/_linalg.py
jmstate/utils/_misc.py
jmstate/utils/_surv.py
jmstate/visualization/__init__.py
jmstate/visualization/_plot.py
jmstate/visualization/_print.py
jmstate-0.5.4.dist-info/licenses/LICENSE
jmstate-0.5.4.dist-info/METADATA
jmstate-0.5.4.dist-info/WHEEL
jmstate-0.5.4.dist-info/top_level.txt
jmstate-0.5.4.dist-info/RECORD
