Metadata-Version: 2.4
Name: jmstate
Version: 0.5.4
Summary: Joint modeling with automatic differentiation
Author-email: Félix Laplante <felixlaplante0@proton.me>
Project-URL: Source, https://gitlab.com/felixlaplante0/jmstate
Classifier: Programming Language :: Python :: 3
Classifier: Operating System :: POSIX :: Linux
Classifier: Operating System :: MacOS
Classifier: Operating System :: Microsoft :: Windows
Requires-Python: >=3.10
License-File: LICENSE
Requires-Dist: numpy
Requires-Dist: torch
Requires-Dist: matplotlib
Requires-Dist: rich
Requires-Dist: pydantic
Requires-Dist: xxhash
Requires-Dist: tqdm
Dynamic: license-file
